vstcompile/__init__.py
vstcompile/github.py
vstcompile/utils.py
vstcompile-3.0.0.dist-info/LICENSE
vstcompile-3.0.0.dist-info/METADATA
vstcompile-3.0.0.dist-info/NOTICE
vstcompile-3.0.0.dist-info/WHEEL
vstcompile-3.0.0.dist-info/top_level.txt
vstcompile-3.0.0.dist-info/RECORD
