Metadata-Version: 2.1
Name: vstcompile
Version: 3.0.0
Summary: VST util for easy compile
Author-email: VST Consulting <sergey.k@vstconsulting.net>
License: Apache License 2.0
Project-URL: Home, https://github.com/vstconsulting/vstcompile
Project-URL: Issue Tracker, https://gitlab.com/vstconsulting/vstcompile/issues
Project-URL: Source Code, https://gitlab.com/vstconsulting/vstcompile
Project-URL: Releases, https://pypi.org/project/vstcompile/#history
Classifier: Development Status :: 5 - Production/Stable
Classifier: Operating System :: POSIX
Classifier: License :: OSI Approved :: Apache Software License
Classifier: Programming Language :: Python
Classifier: Programming Language :: Python :: 3
Classifier: Programming Language :: Python :: 3 :: Only
Classifier: Programming Language :: Python :: 3.8
Classifier: Programming Language :: Python :: 3.9
Classifier: Programming Language :: Python :: 3.10
Classifier: Programming Language :: Python :: 3.11
Classifier: Programming Language :: Python :: Implementation :: CPython
Classifier: Topic :: Software Development :: Libraries
Classifier: Topic :: Software Development :: Libraries :: Python Modules
Classifier: Topic :: Utilities
Requires-Python: >=3.8
License-File: LICENSE
License-File: NOTICE
Provides-Extra: cython
Requires-Dist: cython >=0.29.36 ; extra == 'cython'
Provides-Extra: release
Requires-Dist: githubrelease ~=1.5.9 ; extra == 'release'
